panda3d_gemstone/__init__.py
panda3d_gemstone/__version__.py
panda3d_gemstone/application/__init__.py
panda3d_gemstone/application/application.py
panda3d_gemstone/application/constants.py
panda3d_gemstone/application/events.py
panda3d_gemstone/application/launcher.py
panda3d_gemstone/application/version.py
panda3d_gemstone/controllers/__init__.py
panda3d_gemstone/controllers/avatar.py
panda3d_gemstone/controllers/basic.py
panda3d_gemstone/controllers/camera.py
panda3d_gemstone/controllers/movement.py
panda3d_gemstone/controllers/physics.py
panda3d_gemstone/distributed/__init__.py
panda3d_gemstone/distributed/repository.py
panda3d_gemstone/editor/__init__.py
panda3d_gemstone/editor/__main__.py
panda3d_gemstone/editor/application.py
panda3d_gemstone/editor/launcher.py
panda3d_gemstone/editor/level.py
panda3d_gemstone/editor/showbase.py
panda3d_gemstone/editor/styles.py
panda3d_gemstone/editor/window.py
panda3d_gemstone/editor/gizmos/__init__.py
panda3d_gemstone/editor/gizmos/gizmo.py
panda3d_gemstone/editor/gizmos/grid.py
panda3d_gemstone/editor/widgets/__init__.py
panda3d_gemstone/editor/widgets/level_viewer.py
panda3d_gemstone/editor/widgets/menu.py
panda3d_gemstone/editor/widgets/menubar.py
panda3d_gemstone/editor/widgets/object_library.py
panda3d_gemstone/editor/widgets/panda.py
panda3d_gemstone/editor/widgets/statusbar.py
panda3d_gemstone/engine/__init__.py
panda3d_gemstone/engine/audio.py
panda3d_gemstone/engine/camera.py
panda3d_gemstone/engine/collisions.py
panda3d_gemstone/engine/constants.py
panda3d_gemstone/engine/fog.py
panda3d_gemstone/engine/fsm.py
panda3d_gemstone/engine/graphics.py
panda3d_gemstone/engine/http.py
panda3d_gemstone/engine/inspector.py
panda3d_gemstone/engine/interval.py
panda3d_gemstone/engine/lighting.py
panda3d_gemstone/engine/loader.py
panda3d_gemstone/engine/messenger.py
panda3d_gemstone/engine/model.py
panda3d_gemstone/engine/model_utilities.py
panda3d_gemstone/engine/mouse.py
panda3d_gemstone/engine/node.py
panda3d_gemstone-1.0.0.dist-info/LICENSE
panda3d_gemstone-1.0.0.dist-info/METADATA
panda3d_gemstone-1.0.0.dist-info/WHEEL
panda3d_gemstone-1.0.0.dist-info/top_level.txt
panda3d_gemstone-1.0.0.dist-info/RECORD
