Metadata-Version: 2.1
Name: panda3d_gemstone
Version: 1.0.0
Summary: top level framework built for the Panda3D game engine
Home-page: https://github.com/thetestgame/panda3d-gemstone
Author: Jordan Maxwell
License: MIT
Classifier: Development Status :: 2 - Pre-Alpha
Classifier: Natural Language :: English
Classifier: Programming Language :: Python :: 3
License-File: LICENSE
